arrayscaler/__init__.py
arrayscaler/arrayscaler.py
arrayscaler-0.1.1.dist-info/METADATA
arrayscaler-0.1.1.dist-info/WHEEL
arrayscaler-0.1.1.dist-info/RECORD
