Metadata-Version: 2.1
Name: arrayscaler
Version: 0.1.1
Summary: A simple python code for Scale arrays
Author-email: Eloghosa Ikponmwoba <eloghosaefficiency@gmail.com>
License: MIT License
Keywords: computation,maths,numerical operation
Requires-Python: >=3.11
Requires-Dist: numpy<2,>=1
Provides-Extra: dev
Requires-Dist: ipython; extra == 'dev'
Requires-Dist: jupyterlab; extra == 'dev'
Provides-Extra: lint
Requires-Dist: pre-commit>=2.20.0; extra == 'lint'
Provides-Extra: test
Requires-Dist: pytest<8,>=7; extra == 'test'
